setup.py
db_probability/Binomialdistribution.py
db_probability/Gaussiandistribution.py
db_probability/Generaldistribution.py
db_probability/__init__.py
db_probability.egg-info/PKG-INFO
db_probability.egg-info/SOURCES.txt
db_probability.egg-info/dependency_links.txt
db_probability.egg-info/not-zip-safe
db_probability.egg-info/top_level.txt