Metadata-Version: 1.0
Name: db-probability
Version: 0.1
Summary: Gaussian distributions and Binomial distribution
Home-page: UNKNOWN
Author: Saurabh Ashoka
Author-email: saurabhashok93@gmail.com
License: UNKNOWN
Platform: UNKNOWN
